{
  "model_name": "pierluigic/xl-lexeme",
  "pooling": "mean",
  "batch_size": 32,
  "device": "cuda",
  "lexeme_layers": {
    "pflaster": [
      14,
      18,
      21,
      24
    ],
    "maske": [
      14,
      18,
      21,
      24
    ],
    "kurs": [
      14,
      18,
      21,
      24
    ],
    "fu\u00df": [
      14,
      18,
      21,
      24
    ],
    "blatt": [
      14,
      18,
      21,
      24
    ],
    "block": [
      14,
      18,
      21,
      24
    ],
    "klappe": [
      14,
      18,
      21,
      24
    ],
    "atmosph\u00e4re": [
      14,
      18,
      21,
      24
    ],
    "tor": [
      14,
      18,
      21,
      24
    ],
    "buch": [
      14,
      18,
      21,
      24
    ],
    "bank": [
      14,
      18,
      21,
      24
    ],
    "virus": [
      14,
      18,
      21,
      24
    ],
    "fl\u00fcgel": [
      14,
      18,
      21,
      24
    ],
    "zeitung": [
      14,
      18,
      21,
      24
    ],
    "universit\u00e4t": [
      14,
      18,
      21,
      24
    ],
    "decke": [
      14,
      18,
      21,
      24
    ],
    "schimmel": [
      14,
      18,
      21,
      24
    ],
    "diarium": [
      14,
      18,
      21,
      24
    ],
    "gesichtsmaske": [
      14,
      18,
      21,
      24
    ],
    "kartenspiel": [
      14,
      18,
      21,
      24
    ],
    "kasse": [
      14,
      18,
      21,
      24
    ],
    "klima": [
      14,
      18,
      21,
      24
    ],
    "pinsel": [
      14,
      18,
      21,
      24
    ],
    "richtung": [
      14,
      18,
      21,
      24
    ],
    "schnabel": [
      14,
      18,
      21,
      24
    ],
    "stammbuch": [
      14,
      18,
      21,
      24
    ]
  }
}